notora/__init__.py
notora/py.typed
notora/types.py
notora/utils/__init__.py
notora/utils/time.py
notora/utils/validation.py
notora/v1/__init__.py
notora/v1/enums/__init__.py
notora/v1/enums/base.py
notora/v1/exceptions/__init__.py
notora/v1/exceptions/common.py
notora/v1/models/__init__.py
notora/v1/models/base.py
notora/v1/persistence/__init__.py
notora/v1/persistence/repos/__init__.py
notora/v1/persistence/repos/base.py
notora/v1/schemas/__init__.py
notora/v1/schemas/base.py
notora/v1/services/__init__.py
notora/v1/services/base.py
notora/v2/__init__.py
notora/v2/enums/__init__.py
notora/v2/enums/base.py
notora/v2/exceptions/__init__.py
notora/v2/exceptions/common.py
notora/v2/models/__init__.py
notora/v2/models/base.py
notora/v2/repositories/__init__.py
notora/v2/repositories/base.py
notora/v2/repositories/config.py
notora/v2/repositories/factory.py
notora/v2/repositories/params.py
notora/v2/repositories/query_dsl.py
notora/v2/repositories/types.py
notora/v2/repositories/mixins/__init__.py
notora/v2/repositories/mixins/query.py
notora/v2/repositories/mixins/write.py
notora/v2/schemas/__init__.py
notora/v2/schemas/base.py
notora/v2/services/__init__.py
notora/v2/services/base.py
notora/v2/services/config.py
notora/v2/services/factory.py
notora/v2/services/mixins/__init__.py
notora/v2/services/mixins/accessors.py
notora/v2/services/mixins/create.py
notora/v2/services/mixins/create.pyi
notora/v2/services/mixins/delete.py
notora/v2/services/mixins/executor.py
notora/v2/services/mixins/listing.py
notora/v2/services/mixins/listing.pyi
notora/v2/services/mixins/m2m.py
notora/v2/services/mixins/pagination.py
notora/v2/services/mixins/pagination.pyi
notora/v2/services/mixins/payload.py
notora/v2/services/mixins/retrieval.py
notora/v2/services/mixins/retrieval.pyi
notora/v2/services/mixins/serializer.py
notora/v2/services/mixins/serializer.pyi
notora/v2/services/mixins/update.py
notora/v2/services/mixins/update.pyi
notora/v2/services/mixins/updated_by.py
notora-0.9.0.dist-info/METADATA
notora-0.9.0.dist-info/WHEEL
notora-0.9.0.dist-info/licenses/LICENSE
notora-0.9.0.dist-info/RECORD
