Metadata-Version: 2.4
Name: notora
Version: 0.9.0
Summary: Shared base logic used across AldanDev projects.
Project-URL: Homepage, https://pypi.org/project/notora/
Project-URL: Repository, https://github.com/AldanDev/Notora
Project-URL: Issues, https://github.com/AldanDev/Notora/issues
Author-email: Ivan Larin <ivan.l@aldandev.com>, Igor Pavlyukovets <igor.p@aldandev.com>, Ilia Boiarintsev <ilya.b@aldandev.com>
License: MIT License
License-File: LICENSE
Classifier: Development Status :: 3 - Alpha
Classifier: Intended Audience :: Developers
Classifier: License :: OSI Approved :: MIT License
Classifier: Operating System :: OS Independent
Classifier: Programming Language :: Python :: 3
Classifier: Programming Language :: Python :: 3 :: Only
Classifier: Programming Language :: Python :: 3.12
Classifier: Programming Language :: Python :: 3.13
Classifier: Programming Language :: Python :: 3.14
Classifier: Topic :: Software Development :: Libraries
Requires-Python: <4,>=3.12
Requires-Dist: pydantic[email]<3.0.0,>=2.12.4
Requires-Dist: sqlalchemy[asyncio]<3.0.0,>=2.0.44
